[{"line":2,"elements":[{"start_timestamp":"2022-12-23T13:27:44.351Z","line":5,"name":"As a user i should be able to login","description":"","id":"login;as-a-user-i-should-be-able-to-login","type":"scenario","keyword":"Scenario","steps":[{"result":{"duration":3798136700,"status":"passed"},"line":6,"name":"navigate to url","match":{"location":"app.bersama.steps.CommonStep.navigate_to_url()"},"keyword":"Given "},{"result":{"duration":1832371000,"status":"passed"},"line":7,"name":"login as \"valid_credential\"","match":{"arguments":[{"val":"\"valid_credential\"","offset":9}],"location":"app.bersama.steps.CommonStep.loginAs(java.lang.String)"},"keyword":"When "},{"result":{"duration":16996100,"status":"passed"},"line":8,"name":"current url should be \"https://secondhand-store.herokuapp.com/\"","match":{"arguments":[{"val":"\"https://secondhand-store.herokuapp.com/\"","offset":22}],"location":"app.bersama.steps.CommonStep.currentUrlShouldBe(java.lang.String)"},"keyword":"Then "}],"tags":[{"name":"@login"},{"name":"@login"},{"name":"@positive"}]}],"name":"Login","description":"","id":"login","keyword":"Feature","uri":"file:features/Login.feature","tags":[{"name":"@login","type":"Tag","location":{"line":1,"column":1}}]}]